Metadata-Version: 1.0
Name: pythonhtml
Version: 1.0.0
Summary: This is html module created for embbeding HTML with Python
Home-page: UNKNOWN
Author: prajwal_15
Author-email: prajwalrishabh@gmail.com
License: UNKNOWN
Platform: UNKNOWN
